slicksmith_ttom/__init__.py
slicksmith_ttom/download.py
slicksmith_ttom/main.py
slicksmith_ttom/utils.py
slicksmith_ttom/vis.py
slicksmith_ttom/deep_learning/BalancedRandomGeoSampler.py
slicksmith_ttom/deep_learning/__init__.py
slicksmith_ttom/deep_learning/torchgeo_datasets.py
slicksmith_ttom/deep_learning/utils.py
slicksmith_ttom/preprocessing/__init__.py
slicksmith_ttom/preprocessing/add_georef_and_timestamps.py
slicksmith_ttom-0.1.1.dist-info/METADATA
slicksmith_ttom-0.1.1.dist-info/WHEEL
slicksmith_ttom-0.1.1.dist-info/licenses/LICENSE
slicksmith_ttom-0.1.1.dist-info/RECORD
