Metadata-Version: 2.4
Name: slicksmith_ttom
Version: 0.1.1
Summary: Add your description here
Author-email: Halyjo <harald.l.joakimsen@uit.no>
License-File: LICENSE
Requires-Python: >=3.11
Requires-Dist: lightning>=2.4
Requires-Dist: py7zr>=0.22.0
Requires-Dist: rasterio>=1.4.3
Requires-Dist: torch>=2.7.0
Requires-Dist: torchgeo>=0.7.0
Requires-Dist: typed-argument-parser
